README.md
setup.cfg
setup.py
corona_api/__init__.py
corona_api/client.py
corona_api/endpoints.py
corona_api/exceptions.py
corona_api/request.py
corona_api/statistics.py
corona_api/utils.py
corona_api.egg-info/PKG-INFO
corona_api.egg-info/SOURCES.txt
corona_api.egg-info/dependency_links.txt
corona_api.egg-info/requires.txt
corona_api.egg-info/top_level.txt