Metadata-Version: 2.1
Name: corona-api
Version: 0.8.8
Summary: An asynchronous wrapper for the corona.lmao.ninja API written in Python.
Home-page: https://github.com/apex2504/python-corona-api
Author: Rob Wainwright
Author-email: wainwrightbobby@gmail.com
License: MIT
Keywords: coronavirus,covid-19
Platform: UNKNOWN
Classifier: Development Status :: 5 - Production/Stable
Classifier: License :: OSI Approved :: MIT License
Classifier: Programming Language :: Python :: 3
Classifier: Programming Language :: Python :: 3.5
Classifier: Programming Language :: Python :: 3.6
Classifier: Programming Language :: Python :: 3.7
Classifier: Programming Language :: Python :: 3.8
